[
  {
    "relation": ["delegate_permission/common.handle_all_urls"],
    "target": {
      "namespace": "android_app",
      "package_name": "jp.zyyx.oha.jumpapp.dev.trader",
      "sha256_cert_fingerprints": [
        "EB:DA:67:02:BB:B6:0E:A8:F3:AB:9B:FF:77:C2:96:B6:F3:81:F4:35:57:C9:87:A3:04:1D:85:BF:7E:41:C9:9B",
        "C5:A9:38:27:B3:FE:D0:7A:08:B7:13:26:F2:F1:90:CC:E9:CC:9A:D5:17:AA:D0:81:1D:09:C2:2E:B7:E0:5C:5B",
        "91:A9:7B:81:24:7C:3E:78:C1:27:73:44:85:99:50:4D:19:5E:45:AC:DD:99:24:E7:58:9F:AC:0F:C6:F0:01:0D"
      ]
    }
  },
  {
    "relation": ["delegate_permission/common.handle_all_urls"],
    "target": {
      "namespace": "android_app",
      "package_name": "com.shingenpro",
      "sha256_cert_fingerprints": [
        "EB:DA:67:02:BB:B6:0E:A8:F3:AB:9B:FF:77:C2:96:B6:F3:81:F4:35:57:C9:87:A3:04:1D:85:BF:7E:41:C9:9B",
        "C5:A9:38:27:B3:FE:D0:7A:08:B7:13:26:F2:F1:90:CC:E9:CC:9A:D5:17:AA:D0:81:1D:09:C2:2E:B7:E0:5C:5B",
        "91:A9:7B:81:24:7C:3E:78:C1:27:73:44:85:99:50:4D:19:5E:45:AC:DD:99:24:E7:58:9F:AC:0F:C6:F0:01:0D"
      ]
    }
  }
]
